{
 "generated_utc": "2026-07-16T23:01:10+00:00",
 "stale_after_secs": 300,
 "date": "2026-07-16",
 "pipe_health": {
  "directives_pending": 0,
  "last_processed_clock": "6:18pm",
  "last_processed_iso": "2026-07-16T22:18:03Z",
  "newest_directive_clock": "",
  "newest_directive_iso": null,
  "source": "director inbox",
  "anchor": "inbox files + delivered/processed trail",
  "as_of": "2026-07-16T22:18:03Z"
 },
 "scout": {
  "alive": true,
  "last_poll_utc": "2026-07-16T23:00:18Z",
  "age_s": 53,
  "cycles": 28,
  "label": "scout: alive, last poll 53s ago",
  "anchor": "heartbeat.json+scout.log"
 },
 "coordinator": {
  "alive": true,
  "last_heartbeat_utc": "2026-07-16T23:01:08Z"
 },
 "beacon": {
  "state": "active",
  "idle_since_clock": "",
  "usage_resets_clock": "",
  "note": ""
 },
 "generated_et": "Jul 16, 7:01pm ET"
}